MANIFEST.in
README.md
requirements.txt
setup.py
joker/textmanip/__init__.py
joker/textmanip/__main__.py
joker/textmanip/align.py
joker/textmanip/charset.py
joker/textmanip/cjk.py
joker/textmanip/draw.py
joker/textmanip/path.py
joker/textmanip/regex.py
joker/textmanip/stream.py
joker/textmanip/tabular.py
joker/textmanip/url.py
joker/textmanip/useragent.py
joker/textmanip/data/encodings.txt
joker/textmanip/data/mfc-jp.txt
joker/textmanip/data/mfc-sc.txt
joker/textmanip/data/mfc-tc.txt
joker/textmanip/data/unicode_blocks.txt
joker_textmanip.egg-info/PKG-INFO
joker_textmanip.egg-info/SOURCES.txt
joker_textmanip.egg-info/dependency_links.txt
joker_textmanip.egg-info/entry_points.txt
joker_textmanip.egg-info/namespace_packages.txt
joker_textmanip.egg-info/not-zip-safe
joker_textmanip.egg-info/requires.txt
joker_textmanip.egg-info/top_level.txt
tests/test_align.py
tests/test_cjk.py
tests/test_data.py
tests/test_path.py
tests/test_regex.py
tests/test_tmanip.py
tests/test_url.py
tests/test_useragent.py
tests/xp_atomic_tailer.py